LICENSE
MANIFEST.in
README.rst
setup.py
django_superuser.egg-info/PKG-INFO
django_superuser.egg-info/SOURCES.txt
django_superuser.egg-info/dependency_links.txt
django_superuser.egg-info/not-zip-safe
django_superuser.egg-info/top_level.txt
superuser/__init__.py
superuser/middleware.py